easierSDK/__init__.py
easierSDK/datasetsAPI.py
easierSDK/easier.py
easierSDK/main.py
easierSDK/modelsAPI.py
easierSDK/classes/__init__.py
easierSDK/classes/categories.py
easierSDK/classes/category_metadata.py
easierSDK/classes/constants.py
easierSDK/classes/dataset_metadata.py
easierSDK/classes/easier_model.py
easierSDK/classes/model_metadata.py
easierSDK/classes/repository_metadata.py
easierSDK/classes/training_metadata.py
easierSDK/serving/__init__.py
easierSDK/serving/easier_serving_config_map.py
easierSDK/serving/easier_serving_deployment.py
easierSDK/serving/easier_serving_ingress.py
easierSDK/serving/easier_serving_service.py
easierSDK/serving/entrypoint.py
easierSDK/serving/servingAPI.py
easierSDK/training/__init__.py
easierSDK/training/easier_training_config_map.py
easierSDK/training/easier_training_deployment.py
easierSDK/training/easier_training_ingress.py
easierSDK/training/easier_training_paralel_deployment.py
easierSDK/training/easier_training_persisten_volume.py
easierSDK/training/easier_training_persisten_volume_claim.py
easierSDK/training/easier_training_service.py
easierSDK/training/entrypoint_training.py
easierSDK/training/trainingAPI.py
easierSDK-0.0.79.dist-info/LICENSE
easierSDK-0.0.79.dist-info/METADATA
easierSDK-0.0.79.dist-info/WHEEL
easierSDK-0.0.79.dist-info/top_level.txt
easierSDK-0.0.79.dist-info/RECORD
