Metadata-Version: 2.1
Name: easierSDK
Version: 0.0.79
Summary: This library contains code for interacting with EASIER.AI platform in Python.
Home-page: https://scm.atosresearch.eu/ari/easier/easier-sdk
Author: AIDR Unit
Author-email: adrian.arroyo@atos.net
License: ATOS
Platform: UNKNOWN
Requires-Dist: minio (==6.0.0)
Requires-Dist: tensorflow (>=1.14.0)
Requires-Dist: joblib (>=0.17.0)
Requires-Dist: scikit-learn (==0.23.2)
Requires-Dist: seaborn (>=0.11.0)
Requires-Dist: pandas (>=1.1.4)
Requires-Dist: h5py (<3.0.0)
Requires-Dist: Pillow (==8.1.0)
Requires-Dist: matplotlib (==3.3.4)
Requires-Dist: kubernetes (==12.0.1)
